perscode/__init__.py
perscode/pbow.py
perscode/pvlad.py
perscode/spbow.py
perscode/spvlad.py
perscode/utils.py
perscode/wpbow.py
perscode-0.0.1.dist-info/LICENSE
perscode-0.0.1.dist-info/METADATA
perscode-0.0.1.dist-info/WHEEL
perscode-0.0.1.dist-info/top_level.txt
perscode-0.0.1.dist-info/RECORD
