Metadata-Version: 2.1
Name: perscode
Version: 0.0.1
Summary: Representation of persistence diagrams using persistence codebooks
Home-page: https://github.com/chronchi/perscode
Author: Carlos Ronchi and Lun Zhang
Author-email: carloshvronchi@gmail.com
License: MIT
Keywords: persistent homology,persistence codebooks,persistence diagrams,topological
Platform: UNKNOWN
Classifier: Development Status :: 3 - Alpha
Classifier: Intended Audience :: Science/Research
Classifier: Intended Audience :: Education
Classifier: Intended Audience :: Financial and Insurance Industry
Classifier: Intended Audience :: Healthcare Industry
Classifier: Topic :: Scientific/Engineering :: Information Analysis
Classifier: Topic :: Scientific/Engineering :: Mathematics
Classifier: License :: OSI Approved :: MIT License
Classifier: Programming Language :: Python :: 2.7
Classifier: Programming Language :: Python :: 3
Classifier: Programming Language :: Python :: 3.4
Classifier: Programming Language :: Python :: 3.5
Classifier: Programming Language :: Python :: 3.6
Classifier: Programming Language :: Python :: 3.7
Requires-Dist: scikit-learn
Requires-Dist: numpy
